watchdog_client/__init__.py
skale_watchdog_client-3.1.0.dist-info/METADATA
skale_watchdog_client-3.1.0.dist-info/WHEEL
skale_watchdog_client-3.1.0.dist-info/licenses/LICENSE
skale_watchdog_client-3.1.0.dist-info/RECORD
