Metadata-Version: 2.4
Name: skale-watchdog-client
Version: 3.1.0
Summary: SKALE Watchdog Client - SKALE and FAIR Nodes Health Checks
Project-URL: Homepage, https://github.com/skalenetwork/skale-watchdog
Author-email: SKALE Labs <support@skalelabs.com>
License:                     GNU AFFERO GENERAL PUBLIC LICENSE
License-File: LICENSE
Keywords: skale
Classifier: Development Status :: 5 - Production/Stable
Classifier: Intended Audience :: Developers
Classifier: Natural Language :: English
Classifier: Programming Language :: Python :: 3.13
Requires-Python: <4,>=3.13
Requires-Dist: requests>=2.31.0
Provides-Extra: dev
Requires-Dist: build>=1.2.1; extra == 'dev'
Requires-Dist: twine<7,>=5.0.0; extra == 'dev'
